Metadata-Version: 1.2
Name: alibabacloud-dkms-gcs-python2
Version: 0.0.5
Summary: AlibabaCloud DKMS-GCS SDK for Python2
Home-page: https://github.com/aliyun/alibabacloud-dkms-gcs-python2-sdk
Author: Alibaba Cloud SDK
Author-email: sdk-team@alibabacloud.com
License: Apache License 2.0
Keywords: alibabacloud,dkms_gcs_sdk
Platform: any
Classifier: Development Status :: 4 - Beta
Classifier: Intended Audience :: Developers
Classifier: License :: OSI Approved :: Apache Software License
Classifier: Programming Language :: Python
Classifier: Programming Language :: Python :: 2
Classifier: Programming Language :: Python :: 2.7
Classifier: Topic :: Software Development
Requires-Python: >=2.7
